nameko_django/__init__.py
nameko_django/serializer.py
nameko_django-1.0.0.dist-info/LICENSE
nameko_django-1.0.0.dist-info/METADATA
nameko_django-1.0.0.dist-info/WHEEL
nameko_django-1.0.0.dist-info/entry_points.txt
nameko_django-1.0.0.dist-info/top_level.txt
nameko_django-1.0.0.dist-info/RECORD
