Metadata-Version: 2.1
Name: nameko-django
Version: 1.0.0
Summary: Django intergration for nameko microservice framework.
Home-page: https://github.com/tranvietanh1991/nameko-django
Author: Vincent Anh Tran
Author-email: tranvietanh1991@gmail.com
Maintainer: Vincent Anh Tran
Maintainer-email: vincent.tran@bentoinvest.cloud
License: GPLv2
Platform: UNKNOWN
Classifier: Development Status :: 4 - Beta
Classifier: Intended Audience :: Developers
Classifier: Programming Language :: Python :: 2
Classifier: Programming Language :: Python :: 2.7
Classifier: Programming Language :: Python :: 3
Classifier: Programming Language :: Python :: 3.5
Classifier: Programming Language :: Python :: 3.6
Classifier: Programming Language :: Python :: 3.7
Classifier: Operating System :: OS Independent
Classifier: Topic :: Software Development :: Libraries :: Python Modules
Requires-Dist: nameko (>=2.11.0)
Requires-Dist: django (>=1.10)
Requires-Dist: msgpack (>=0.5.0)
